manifester/__init__.py
manifester/_settings.py
manifester/commands.py
manifester/helpers.py
manifester/logger.py
manifester/manifester.py
manifester/settings.py
manifester-0.2.13.dist-info/licenses/LICENSE
manifester-0.2.13.dist-info/METADATA
manifester-0.2.13.dist-info/WHEEL
manifester-0.2.13.dist-info/entry_points.txt
manifester-0.2.13.dist-info/top_level.txt
manifester-0.2.13.dist-info/RECORD
