Metadata-Version: 2.4
Name: manifester
Version: 0.2.13
Summary: Red Hat subscriptions made manifest.
Author-email: Danny Synk <dsynk@redhat.com>
License:                                  Apache License
Project-URL: Repository, https://github.com/SatelliteQE/manifester
Keywords: manifester,RHSM
Classifier: Development Status :: 4 - Beta
Classifier: Intended Audience :: Developers
Classifier: License :: OSI Approved :: Apache Software License
Classifier: Natural Language :: English
Classifier: Programming Language :: Python :: 3
Classifier: Programming Language :: Python :: 3.10
Classifier: Programming Language :: Python :: 3.11
Classifier: Programming Language :: Python :: 3.12
Requires-Python: >=3.10
License-File: LICENSE
Requires-Dist: click
Requires-Dist: dynaconf[vault]
Requires-Dist: logzero
Requires-Dist: pytest
Requires-Dist: pyyaml
Requires-Dist: requests
Requires-Dist: setuptools
Provides-Extra: dev
Requires-Dist: pre-commit; extra == "dev"
Requires-Dist: pytest; extra == "dev"
Requires-Dist: ruff; extra == "dev"
Provides-Extra: setup
Requires-Dist: build; extra == "setup"
Requires-Dist: twine; extra == "setup"
Dynamic: license-file
